pyflexlab/__init__.py
pyflexlab/auxiliary.py
pyflexlab/constants.py
pyflexlab/data_process.py
pyflexlab/equip_wrapper.py
pyflexlab/file_organizer.py
pyflexlab/measure_flow.py
pyflexlab/measure_manager.py
pyflexlab/simulated.py
pyflexlab/drivers/Keithley_6430.py
pyflexlab/drivers/MercuryiPS_VISA.py
pyflexlab/drivers/SR860.py
pyflexlab/drivers/__init__.py
pyflexlab/drivers/keithley6221.py
pyflexlab/drivers/keysight_b2902b.py
pyflexlab/drivers/laser.py
pyflexlab/drivers/mercuryITC.py
pyflexlab/drivers/probe_rotator.py
pyflexlab/pltconfig/__init__.py
pyflexlab/pltconfig/color_preset.py
pyflexlab/pltconfig/plot_config_notex.py
pyflexlab/pltconfig/plot_config_tex.py
pyflexlab/pltconfig/plot_config_tex_pgf.py
pyflexlab/pltconfig/rand_color.json
pyflexlab/templates/assist_measure.ipynb
pyflexlab/templates/assist_post.ipynb
pyflexlab/templates/measure_types.json
pyflexlab-1.0.dist-info/licenses/LICENSE
pyflexlab-1.0.dist-info/METADATA
pyflexlab-1.0.dist-info/WHEEL
pyflexlab-1.0.dist-info/entry_points.txt
pyflexlab-1.0.dist-info/top_level.txt
pyflexlab-1.0.dist-info/RECORD
