Metadata-Version: 2.4
Name: pyflexlab
Version: 1.0
Summary: Integrated Tools for Electronic, Cryogenic and Magnetic Measurements
Author-email: Dongkai <dongkai001@e.ntu.edu.sg>
License-Expression: MIT
Project-URL: Homepage, https://github.com/panasee/pyflexlab
Keywords: measurement,instrumentation
Classifier: Development Status :: 4 - Beta
Classifier: Programming Language :: Python
Classifier: Intended Audience :: Science/Research
Classifier: Topic :: Scientific/Engineering :: Physics
Requires-Python: >=3.11
License-File: LICENSE
Requires-Dist: numpy
Requires-Dist: pandas
Requires-Dist: matplotlib
Requires-Dist: plotly>=5.24.1
Requires-Dist: kaleido==0.1.0.post1
Requires-Dist: pyvisa
Requires-Dist: pyvisa-py
Requires-Dist: pymeasure>=0.14.0
Requires-Dist: qcodes>=0.47.0
Requires-Dist: jupyter
Requires-Dist: dash
Requires-Dist: prefect
Requires-Dist: pyomnix
Provides-Extra: gui
Requires-Dist: PyQt6; extra == "gui"
Dynamic: license-file
